intelligenceai/__init__.py
intelligenceai/concepts.py
intelligenceai-0.0.1.dist-info/METADATA
intelligenceai-0.0.1.dist-info/WHEEL
intelligenceai-0.0.1.dist-info/licenses/LICENSE
intelligenceai-0.0.1.dist-info/RECORD
